echokit/__init__.py
echokit/echodist.py
echokit/handlers.py
echokit/models.py
echokit/responses.py
echokit-0.3.3.dist-info/DESCRIPTION.rst
echokit-0.3.3.dist-info/METADATA
echokit-0.3.3.dist-info/RECORD
echokit-0.3.3.dist-info/WHEEL
echokit-0.3.3.dist-info/entry_points.txt
echokit-0.3.3.dist-info/metadata.json
echokit-0.3.3.dist-info/top_level.txt
