Metadata-Version: 2.0
Name: echokit
Version: 0.3.3
Summary: Alexa Skills Kit SDK for Python 3.6
Home-page: https://github.com/arcward/echokit
Author: Edward Wells
Author-email: git@edward.sh
License: MIT
Keywords: Amazon AWS Alexa Skills Kit ASK py3 python3.6 lambda
Platform: UNKNOWN
